clinto/__init__.py
clinto/parser.py
clinto/utils.py
clinto/version.py
clinto/ast/__init__.py
clinto/ast/codegen.py
clinto/ast/source_parser.py
clinto/parsers/__init__.py
clinto/parsers/argparse_.py
clinto/parsers/base.py
clinto/parsers/constants.py
clinto/parsers/docopt_.py
clinto/tests/__init__.py
clinto/tests/factories.py
clinto/tests/test_parsers.py
clinto-0.3.0.dist-info/METADATA
clinto-0.3.0.dist-info/RECORD
clinto-0.3.0.dist-info/WHEEL
clinto-0.3.0.dist-info/top_level.txt
