Metadata-Version: 2.1
Name: clinto
Version: 0.3.0
Summary: Clinto
Home-page: http://www.github.com/wooey/clinto
Author: Chris Mitchell
Author-email: chris.mit7@gmail.com
License: UNKNOWN
Platform: UNKNOWN
Classifier: Intended Audience :: Developers
Classifier: Operating System :: OS Independent
Classifier: Programming Language :: Python
Requires-Dist: six
